lexoffice_client/__init__.py
lexoffice_client/client.py
lexoffice_client/common.py
lexoffice_client/contact.py
lexoffice_client/file.py
lexoffice_client/posting_category.py
lexoffice_client/py.typed
lexoffice_client/voucher.py
lexoffice_client/lexoffice_client/__init__.pyi
lexoffice_client/lexoffice_client/client.pyi
lexoffice_client/lexoffice_client/common.pyi
lexoffice_client/lexoffice_client/contact.pyi
lexoffice_client/lexoffice_client/voucher.pyi
lexoffice_client-0.1.5.dist-info/licenses/LICENSE
tests/__init__.py
tests/test_lexoffice_client.py
lexoffice_client-0.1.5.dist-info/METADATA
lexoffice_client-0.1.5.dist-info/WHEEL
lexoffice_client-0.1.5.dist-info/top_level.txt
lexoffice_client-0.1.5.dist-info/RECORD
