Metadata-Version: 2.4
Name: lexoffice-client
Version: 0.1.5
Summary: A Python client for the Lexoffice API
Home-page: https://github.com/jvm986/lexoffice-client
Author: James Maguire
Author-email: jvm986@gmail.com
Classifier: Programming Language :: Python :: 3
Classifier: License :: OSI Approved :: MIT License
Classifier: Operating System :: OS Independent
Requires-Python: >=3.6
License-File: LICENSE
Requires-Dist: email_validator
Requires-Dist: httpx
Requires-Dist: pydantic
Dynamic: author
Dynamic: author-email
Dynamic: classifier
Dynamic: description
Dynamic: description-content-type
Dynamic: home-page
Dynamic: license-file
Dynamic: requires-dist
Dynamic: requires-python
Dynamic: summary
